{
  "series_map": [
    {
      "path": "/series/movie",
      "pagename": "영화",
      "depth2": [
        {
          "path": "/series/movie/1",
          "pagename": "시리즈1"
        },
        {
          "path": "/series/movie/2",
          "pagename": "시리즈2"
        },
        {
          "path": "/series/movie/3",
          "pagename": "시리즈3"
        },
        {
          "path": "/series/movie/4",
          "pagename": "시리즈4"
        },
        {
          "path": "/series/movie/5",
          "pagename": "시리즈5"
        },
        {
          "path": "/series/movie/6",
          "pagename": "시리즈6"
        },
        {
          "path": "/series/movie/7",
          "pagename": "시리즈7"
        },
        {
          "path": "/series/movie/8",
          "pagename": "시리즈8"
        }
      ]
    },
    {
      "path": "/series/book",
      "pagename": "책",
      "depth2": [
        {
          "path": "/series/book/1",
          "pagename": "시리즈1"
        },
        {
          "path": "/series/book/2",
          "pagename": "시리즈2"
        },
        {
          "path": "/series/book/3",
          "pagename": "시리즈3"
        },
        {
          "path": "/series/book/4",
          "pagename": "시리즈4"
        },
        {
          "path": "/series/book/5",
          "pagename": "시리즈5"
        },
        {
          "path": "/series/book/6",
          "pagename": "시리즈6"
        },
        {
          "path": "/series/book/7",
          "pagename": "시리즈7"
        },
        {
          "path": "/series/book/8",
          "pagename": "시리즈8"
        }
      ]
    }
  ]
}
